MANIFEST.in
setup.py
deego/__init__.py
deego/core.py
deego/models.py
deego/version.py
deego.egg-info/PKG-INFO
deego.egg-info/SOURCES.txt
deego.egg-info/dependency_links.txt
deego.egg-info/requires.txt
deego.egg-info/top_level.txt
deego/managers/__init__.py
deego/managers/auto.py
deego/managers/libvirt.xml
deego/managers/lxc.conf
deego/managers/lxc.py
vows/__init__.py
vows/create_vm_vows.py