Metadata-Version: 1.1
Name: deego
Version: 0.2.2
Summary: deego is a vm manager that is dead simple
Home-page: http://heynemann.github.com/deego/
Author: Bernardo Heynemann
Author-email: heynemann@gmail.com
License: MIT
Keywords: virtualization vm lxc vmware virtualbox
Platform: UNKNOWN
Classifier: Development Status :: 3 - Alpha
Classifier: Intended Audience :: Developers
Classifier: License :: OSI Approved :: MIT License
Classifier: Natural Language :: English
Classifier: Operating System :: MacOS
Classifier: Operating System :: POSIX :: Linux
Classifier: Programming Language :: Python :: 2.7
